louvain_numba/__init__.py
louvain_numba/modularity.py
louvain_numba/partitions.py
louvain_numba/typing.py
louvain_numba/utils.py
louvain_numba-0.0.2.dist-info/WHEEL
louvain_numba-0.0.2.dist-info/METADATA
louvain_numba-0.0.2.dist-info/RECORD
