Metadata-Version: 2.1
Name: louvain-numba
Version: 0.0.2
Summary: A package for fast community detection in graphs using the Louvain method with Numba optimization.
License: MIT
Author: Maixent Chenebaux
Author-email: max.chbx@gmail.com
Requires-Python: >=3.10,<4.0
Classifier: License :: OSI Approved :: MIT License
Classifier: Programming Language :: Python :: 3
Classifier: Programming Language :: Python :: 3.10
Requires-Dist: networkx (>=3.1.0,<4.0.0)
Requires-Dist: numba (>=0.58.1,<0.59.0)
Requires-Dist: numpy (>=1.26.2,<2.0.0)
Requires-Dist: scipy (>=1.11.2,<2.0.0)
